Color_RNA/Color_RNA.py
Color_RNA/__init__.py
color_rna-0.5.1.dist-info/METADATA
color_rna-0.5.1.dist-info/WHEEL
color_rna-0.5.1.dist-info/licenses/LICENSE
color_rna-0.5.1.dist-info/RECORD
