Metadata-Version: 2.1
Name: Color_RNA
Version: 0.5.1
Summary: A package allows for generation of colored secondary RNA structure images
Project-URL: Homepage, http://www.triggate.com
Author-email: Efi Moree <efimoree@gmail.com>, Rei Mendel <mendel.rei@gmail.com>
License: MIT License
License-File: LICENSE
Classifier: License :: OSI Approved :: MIT License
Classifier: Operating System :: OS Independent
Classifier: Programming Language :: Python :: 3
Requires-Python: >=3.7
Requires-Dist: pillow>=8.0.1
Requires-Dist: selenium>=4.3.0
